bioh2m/__about__.py
bioh2m/__init__.py
bioh2m/module.py
bioh2m/Data/__init__.py
bioh2m/Data/dict_tx_h.json
bioh2m/Data/dict_tx_m.json
bioh2m/Data/homo_dict.json
bioh2m/Data/homo_dict_mouse.json
bioh2m/Data/human_name_dict.json
bioh2m-1.0.3.dist-info/METADATA
bioh2m-1.0.3.dist-info/WHEEL
bioh2m-1.0.3.dist-info/licenses/LICENSE.txt
bioh2m-1.0.3.dist-info/RECORD
