Metadata-Version: 2.3
Name: bioh2m
Version: 1.0.3
Summary: For precision modeling of human variants in the mouse genome.
Project-URL: Documentation, https://h2m-public.readthedocs.io
Project-URL: Issues, https://github.com/kexindon/h2m-public/issues
Project-URL: Source, https://github.com/kexindon/h2m-public
Author-email: Kexin Dong <gorkordkx@gmail.com>
License: MIT License
License-File: LICENSE.txt
Classifier: Development Status :: 4 - Beta
Classifier: Programming Language :: Python
Classifier: Programming Language :: Python :: 3.8
Classifier: Programming Language :: Python :: 3.9
Classifier: Programming Language :: Python :: 3.10
Classifier: Programming Language :: Python :: 3.11
Classifier: Programming Language :: Python :: 3.12
Classifier: Programming Language :: Python :: Implementation :: CPython
Classifier: Programming Language :: Python :: Implementation :: PyPy
Requires-Python: >=3.9
Requires-Dist: biopython>=1.81
Requires-Dist: gffutils>=0.12
Requires-Dist: matplotlib>=3.7.0
Requires-Dist: numpy>=1.24.2
Requires-Dist: pandas>=1.5.3
Requires-Dist: pybiomart>=0.2.0
Requires-Dist: pysam>=0.22.1
Requires-Dist: requests>=2.26.0
Provides-Extra: doc
Requires-Dist: sphinxawesome-theme; extra == 'doc'
Requires-Dist: sphinx~=4.2.0; extra == 'doc'
